repo_statistics/__init__.py
repo_statistics/classification.py
repo_statistics/commits.py
repo_statistics/constants.py
repo_statistics/contributors.py
repo_statistics/documentation.py
repo_statistics/gini.py
repo_statistics/main.py
repo_statistics/platform.py
repo_statistics/py.typed
repo_statistics/source.py
repo_statistics/timeseries.py
repo_statistics/utils.py
repo_statistics/data/__init__.py
repo_statistics/data/files/additional-formats.yml
repo_statistics/data/files/linguist.yml
repo_statistics/data/files/repo-linter-ruleset.json
repo_statistics/tests/__init__.py
repo_statistics/tests/test_smoke.py
repo_statistics-0.3.0.dist-info/licenses/LICENSE
repo_statistics-0.3.0.dist-info/METADATA
repo_statistics-0.3.0.dist-info/WHEEL
repo_statistics-0.3.0.dist-info/top_level.txt
repo_statistics-0.3.0.dist-info/RECORD
