Metadata-Version: 2.4
Name: repo-statistics
Version: 0.3.0
Summary: Calculate metrics and statistics for source-code repositories.
Author-email: Eva Maxfield Brown <evamaxfieldbrown@gmail.com>
License: MIT License
Project-URL: Homepage, https://github.com/evamaxfield/repo-statistics
Project-URL: Bug Tracker, https://github.com/evamaxfield/repo-statistics/issues
Project-URL: Documentation, https://evamaxfield.github.io/repo-statistics
Project-URL: User Support, https://github.com/evamaxfield/repo-statistics/issues
Classifier: Development Status :: 4 - Beta
Classifier: Natural Language :: English
Classifier: Programming Language :: Python :: 3.11
Classifier: Programming Language :: Python :: 3.12
Classifier: Programming Language :: Python :: 3.13
Requires-Python: >=3.11
License-File: LICENSE
Requires-Dist: backoff<3,>=2
Requires-Dist: dataclasses-json<1,>=0.6
Requires-Dist: gitpython<4,>=3
Requires-Dist: gh-tokens-loader<1,>=0.1.2
Requires-Dist: ghapi<2,>=1
Requires-Dist: numpy<2,>=1
Requires-Dist: scipy<2,>=1
Requires-Dist: polars<2,>=1
Requires-Dist: pygount<4,>=3
Requires-Dist: pyyaml<7,>=6
Requires-Dist: timeout-function-decorator<3,>=2
Requires-Dist: tqdm<5,>=4
Provides-Extra: lint
Requires-Dist: pre-commit>=2.20.0; extra == "lint"
Provides-Extra: dev
Requires-Dist: ipython; extra == "dev"
Requires-Dist: jupyterlab; extra == "dev"
Requires-Dist: pytest>=5.4.3; extra == "dev"
Provides-Extra: coiled
Requires-Dist: coiled<2,>=1; extra == "coiled"
Dynamic: license-file
